browser/__init__.py
interpreter/__init__.py
javascript/__init__.py
pyfyre/__init__.py
pyfyre/decorators.py
pyfyre/events.py
pyfyre/exceptions.py
pyfyre/noderef.py
pyfyre/py.typed
pyfyre/router.py
pyfyre/states.py
pyfyre/styles.py
pyfyre/utils.py
pyfyre/nodes/__init__.py
pyfyre/nodes/base.py
pyfyre/nodes/buttons.py
pyfyre/nodes/futures.py
pyfyre/nodes/inputs.py
pyfyre/nodes/links.py
pyfyre/nodes/lists.py
pyfyre/nodes/widgets.py
pyfyre/presets/__init__.py
pyfyre/presets/errors.py
pyfyre/presets/loading.py
pyfyre_cli/__init__.py
pyfyre_cli/build_app.py
pyfyre_cli/create_app.py
pyfyre_cli/run_app.py
pyfyre_cli/utils.py
pyfyre_cli/web_app.py
pyfyre_cli/__pycache__/__init__.cpython-310.pyc
pyfyre_cli/__pycache__/build_app.cpython-310.pyc
pyfyre_cli/__pycache__/create_app.cpython-310.pyc
pyfyre_cli/__pycache__/run_app.cpython-310.pyc
pyfyre_cli/__pycache__/utils.cpython-310.pyc
pyfyre_cli/__pycache__/web_app.cpython-310.pyc
pyfyre_cli/copybin/brython_stdlib.js
pyfyre_cli/user/.gitignore
pyfyre_cli/user/requirements.txt
pyfyre_cli/user/settings.py
pyfyre_cli/user/template.html
pyfyre_cli/user/public/favicon.ico
pyfyre_cli/user/public/style.css
pyfyre_cli/user/src/index.py
pyfyre-0.6.9.dist-info/AUTHORS
pyfyre-0.6.9.dist-info/LICENSE
pyfyre-0.6.9.dist-info/METADATA
pyfyre-0.6.9.dist-info/WHEEL
pyfyre-0.6.9.dist-info/entry_points.txt
pyfyre-0.6.9.dist-info/top_level.txt
pyfyre-0.6.9.dist-info/RECORD
