Metadata-Version: 2.1
Name: pyfyre
Version: 0.6.9
Summary: A fast, declarative, and incrementally adoptable Python web frontend framework for building reactive web user interfaces.
Home-page: https://pyfyre.netlify.app/
Download-URL: https://pypi.org/project/pyfyre/
Author: StackSpace
Author-email: stackspace.ph@gmail.com
License: MIT
Project-URL: Source, https://github.com/pyfyre/pyfyre
Project-URL: Updates, https://www.facebook.com/pyfyreframework/
Project-URL: Documentation, https://pyfyre-docs.netlify.app/
Project-URL: Community, https://discord.gg/YzEDuqhgZJ
License-File: LICENSE
License-File: AUTHORS
Requires-Dist: brython
Requires-Dist: livereload ==2.6.3
Requires-Dist: python-minifier ==2.8.0
Requires-Dist: autoflake ==1.6.1
Requires-Dist: Flask ==2.2.2
